pgdocgen/__init__.py
pgdocgen/files.py
pgdocgen/output.py
pgdocgen/parser.py
pgdocgen/pgdocgen
pgdocgen/readddl.py
pgdocgen/utils.py
pgdocgen/ddlobject/__init__.py
pgdocgen/ddlobject/db.py
pgdocgen/ddlobject/ddlobject.py
pgdocgen/ddlobject/schema.py
pgdocgen/ddlobject/table.py
pgdocgen/play/test_html/styles/documentation_functions.css
pgdocgen/play/test_html/styles/documentation_index.css
pgdocgen/play/test_html/styles/sprite_fin.png
pgdocgen/play/test_html/styles/common_blocks/d-breadcrumbs/d-breadcrumbs.css
pgdocgen/play/test_html/styles/common_blocks/d-heading/d-heading.css
pgdocgen/play/test_html/styles/common_blocks/d-list/d-list.css
pgdocgen/play/test_html/styles/page_blocks/d-content/d-content.css
pgdocgen/play/test_html/styles/page_blocks/d-footer/d-footer.css
pgdocgen/play/test_html/styles/page_blocks/d-function/d-function.css
pgdocgen/play/test_html/styles/page_blocks/d-functions-list/d-function-list.css
pgdocgen/play/test_html/styles/page_blocks/d-page/d-page.css
pgdocgen/templates/base.mako
pgdocgen/templates/index.mako
pgdocgen/templates/schema.mako
pgdocgen/templates/styles/documentation_functions.css
pgdocgen/templates/styles/documentation_index.css
pgdocgen/templates/styles/sprite_fin.png
pgdocgen/templates/styles/common_blocks/d-breadcrumbs/d-breadcrumbs.css
pgdocgen/templates/styles/common_blocks/d-heading/d-heading.css
pgdocgen/templates/styles/common_blocks/d-list/d-list.css
pgdocgen/templates/styles/page_blocks/d-content/d-content.css
pgdocgen/templates/styles/page_blocks/d-footer/d-footer.css
pgdocgen/templates/styles/page_blocks/d-function/d-function.css
pgdocgen/templates/styles/page_blocks/d-functions-list/d-function-list.css
pgdocgen/templates/styles/page_blocks/d-page/d-page.css
pgdocgen/tests/__init__.py
pgdocgen/tests/base.py
pgdocgen/tests/test_ddl.py
pgdocgen/tests/test_parser.py
pgdocgen/tests/out_html/styles/documentation_functions.css
pgdocgen/tests/out_html/styles/documentation_index.css
pgdocgen-0.4.3.dist-info/METADATA
pgdocgen-0.4.3.dist-info/RECORD
pgdocgen-0.4.3.dist-info/WHEEL
pgdocgen-0.4.3.dist-info/top_level.txt
